lifeweb_crawler/__init__.py
lifeweb_crawler/gm.py
lifeweb_crawler-1.0.1.dist-info/METADATA
lifeweb_crawler-1.0.1.dist-info/WHEEL
lifeweb_crawler-1.0.1.dist-info/top_level.txt
lifeweb_crawler-1.0.1.dist-info/RECORD
